<annotation>
	<folder>class_6</folder>
	<filename>169.tif</filename>
	<path>D:\Program_Data\First\Clear_data\class_6\169.tif</path>
	<source>
		<database>Unknown</database>
	</source>
	<size>
		<width>843</width>
		<height>603</height>
		<depth>1</depth>
	</size>
	<segmented>0</segmented>
	<object>
		<name>2843</name>
		<pose>Unspecified</pose>
		<truncated>0</truncated>
		<difficult>0</difficult>
		<bndbox>
			<xmin>361</xmin>
			<ymin>26</ymin>
			<xmax>715</xmax>
			<ymax>400</ymax>
		</bndbox>
	</object>
</annotation>
